scrapy_feedstreaming-0.0.1-py3.7-nspkg.pth
alexber/feedstreaming/__init__.py
alexber/feedstreaming/export.py
alexber/feedstreaming/data/__init__.py
tests_data/__init__.py
tests_data/tests/__init__.py
scrapy_feedstreaming-0.0.1.dist-info/LICENSE.txt
scrapy_feedstreaming-0.0.1.dist-info/METADATA
scrapy_feedstreaming-0.0.1.dist-info/WHEEL
scrapy_feedstreaming-0.0.1.dist-info/namespace_packages.txt
scrapy_feedstreaming-0.0.1.dist-info/top_level.txt
scrapy_feedstreaming-0.0.1.dist-info/RECORD
