Metadata-Version: 2.1
Name: scrapy-feedstreaming
Version: 0.0.1
Summary: Based on scrapy.extensions.feedexport.FeedExporter to live stream data
Home-page: https://github.com/alex-ber/scrapy-feedstreaming
Author: Alexander Berkovich
License: Apache 2.0
Keywords: Scrapy Feed Exports S3 streaming data online extension plugin
Platform: UNKNOWN
Classifier: Development Status :: 5 - Production/Stable
Classifier: Environment :: Console
Classifier: Intended Audience :: Developers
Classifier: License :: OSI Approved :: BSD License
Classifier: Programming Language :: Python
Classifier: Programming Language :: Python :: 3 :: Only
Classifier: Programming Language :: Python :: 3.6
Classifier: Programming Language :: Python :: 3.7
Classifier: Programming Language :: Python :: 3.8
Classifier: Programming Language :: Python :: 3.9
Classifier: Programming Language :: Python :: Implementation :: CPython
Classifier: Topic :: Utilities
Classifier: Topic :: Software Development :: Libraries :: Python Modules
Classifier: Framework :: Scrapy
Classifier: Operating System :: OS Independent
Classifier: Operating System :: Microsoft :: Windows
Classifier: Operating System :: POSIX
Classifier: Operating System :: Unix
Classifier: Natural Language :: English
Requires-Python: >=3.6
Requires-Dist: Scrapy
Requires-Dist: botocore
Provides-Extra: tests
Requires-Dist: alex-ber-utils (==0.5.2) ; extra == 'tests'
Requires-Dist: atomicwrites (==1.3.0) ; extra == 'tests'
Requires-Dist: attrs (==19.1.0) ; extra == 'tests'
Requires-Dist: colorama (==0.4.1) ; extra == 'tests'
Requires-Dist: mock (==2.0.0) ; extra == 'tests'
Requires-Dist: more-itertools (==6.0.0) ; extra == 'tests'
Requires-Dist: pbr (==5.1.3) ; extra == 'tests'
Requires-Dist: pluggy (==0.9.0) ; extra == 'tests'
Requires-Dist: py (==1.8.0) ; extra == 'tests'
Requires-Dist: pytest (==4.3.1) ; extra == 'tests'
Requires-Dist: pytest-assume (==1.2.2) ; extra == 'tests'
Requires-Dist: pytest-mock (==1.10.1) ; extra == 'tests'
Requires-Dist: PyYAML (==5.1) ; extra == 'tests'
Requires-Dist: six (==1.12.0) ; extra == 'tests'
